easyai4all/client.py
easyai4all/chat_completion/__init__.py
easyai4all/chat_completion/exceptions.py
easyai4all/chat_completion/response.py
easyai4all/chat_completion/models/audio.py
easyai4all/chat_completion/models/base.py
easyai4all/chat_completion/models/message.py
easyai4all/chat_completion/models/tokens.py
easyai4all/chat_completion/models/tools.py
easyai4all/chat_completion/models/usage.py
easyai4all/chat_request/__init__.py
easyai4all/chat_request/content.py
easyai4all/chat_request/messages.py
easyai4all/chat_request/request.py
easyai4all/chat_request/tools.py
easyai4all/providers/__init__.py
easyai4all/providers/base_provider.py
easyai4all/providers/exceptions.py
easyai4all/providers/options/anthropic.py
easyai4all/providers/options/fireworks.py
easyai4all/providers/options/gemini.py
easyai4all/providers/options/ollama.py
easyai4all/providers/options/openai.py
easyai4all-0.3.1.dist-info/METADATA
easyai4all-0.3.1.dist-info/WHEEL
easyai4all-0.3.1.dist-info/licenses/LICENSE
easyai4all-0.3.1.dist-info/RECORD
