Metadata-Version: 2.4
Name: easyai4all
Version: 0.3.1
Summary: EasyAI4All: Unified LLM Interface
Project-URL: Homepage, https://github.com/BRama10/easyai4all
Project-URL: Repository, https://github.com/BRama10/easyai4all.git
License: MIT License
License-File: LICENSE
Keywords: interface,llm,unify
Requires-Python: <3.12,>=3.10
Requires-Dist: httpx
Requires-Dist: python-dotenv
